semantic_comparison_network/__init__.py
semantic_comparison_network/semantic_comparison_network.py
semantic_comparison_network-1.0.8.dist-info/LICENSE.txt
semantic_comparison_network-1.0.8.dist-info/METADATA
semantic_comparison_network-1.0.8.dist-info/WHEEL
semantic_comparison_network-1.0.8.dist-info/top_level.txt
semantic_comparison_network-1.0.8.dist-info/RECORD
