Metadata-Version: 2.2
Name: semantic_comparison_network
Version: 1.0.8
Home-page: https://github.com/sapiens-technology/semantic_comparison_network
Author: SAPIENS TECHNOLOGY
License: Proprietary Software
License-File: LICENSE.txt
Requires-Dist: numpy
Requires-Dist: tiktoken
Requires-Dist: tqdm
Requires-Dist: hurnet
Dynamic: author
Dynamic: home-page
Dynamic: license
Dynamic: requires-dist
